<?xml version="1.0" encoding="windows-1252" ?>
<!DOCTYPE ViewObject SYSTEM "jbo_03_01.dtd">
<!---->
<ViewObject
  xmlns="http://xmlns.oracle.com/bc4j"
  Name="VendhqSaleItemsOnhandView1"
  Version="12.2.1.9.14"
  InheritPersonalization="merge"
  BindingStyle="OracleName"
  CustomQuery="true"
  PageIterMode="Full">
  <DesignTime>
    <Attr Name="_isExpertMode" Value="true"/>
  </DesignTime>
  <SQLQuery><![CDATA[SELECT VendhqSaleItemsOnhand.ROW_ID,
       VendhqSaleItemsOnhand.ORG_CODE,
       VendhqSaleItemsOnhand.SUBINVENTORY,
       VendhqSaleItemsOnhand.ITEM_NUMBER,
       VendhqSaleItemsOnhand.UOM_CODE,
       VendhqSaleItemsOnhand.ONHAND_QTY,
       VendhqSaleItemsOnhand.RESERVED_QTY,
       VendhqSaleItemsOnhand.RECEIVING_QTY,
       VendhqSaleItemsOnhand.LAST_UPDATE_DATE,
       VendhqSaleItemsOnhand.SALE_QTY
FROM VENDHQ_SALE_ITEMS_ONHAND VendhqSaleItemsOnhand]]></SQLQuery>
  <ViewAttribute
    Name="RowId1"
    IsUpdateable="false"
    IsPersistent="false"
    IsNotNull="true"
    PrecisionRule="true"
    Type="java.math.BigDecimal"
    ColumnType="NUMBER"
    AliasName="ROW_ID"
    Expression="ROW_ID"
    SQLType="NUMERIC"/>
  <ViewAttribute
    Name="OrgCode"
    IsUpdateable="false"
    IsPersistent="false"
    IsNotNull="true"
    PrecisionRule="true"
    Precision="20"
    Type="java.lang.String"
    ColumnType="VARCHAR2"
    AliasName="ORG_CODE"
    Expression="ORG_CODE"
    SQLType="VARCHAR">
    <DesignTime>
      <Attr Name="_DisplaySize" Value="20"/>
    </DesignTime>
  </ViewAttribute>
  <ViewAttribute
    Name="Subinventory"
    IsUpdateable="false"
    IsPersistent="false"
    IsNotNull="true"
    PrecisionRule="true"
    Precision="12"
    Type="java.lang.String"
    ColumnType="VARCHAR2"
    AliasName="SUBINVENTORY"
    Expression="SUBINVENTORY"
    SQLType="VARCHAR">
    <DesignTime>
      <Attr Name="_DisplaySize" Value="12"/>
    </DesignTime>
  </ViewAttribute>
  <ViewAttribute
    Name="ItemNumber"
    IsUpdateable="false"
    IsPersistent="false"
    IsNotNull="true"
    PrecisionRule="true"
    Precision="20"
    Type="java.lang.String"
    ColumnType="VARCHAR2"
    AliasName="ITEM_NUMBER"
    Expression="ITEM_NUMBER"
    SQLType="VARCHAR">
    <DesignTime>
      <Attr Name="_DisplaySize" Value="20"/>
    </DesignTime>
  </ViewAttribute>
  <ViewAttribute
    Name="UomCode"
    IsUpdateable="false"
    IsPersistent="false"
    IsNotNull="true"
    PrecisionRule="true"
    Precision="5"
    Type="java.lang.String"
    ColumnType="VARCHAR2"
    AliasName="UOM_CODE"
    Expression="UOM_CODE"
    SQLType="VARCHAR">
    <DesignTime>
      <Attr Name="_DisplaySize" Value="5"/>
    </DesignTime>
  </ViewAttribute>
  <ViewAttribute
    Name="OnhandQty"
    IsUpdateable="false"
    IsPersistent="false"
    PrecisionRule="true"
    Type="java.math.BigDecimal"
    ColumnType="NUMBER"
    AliasName="ONHAND_QTY"
    Expression="ONHAND_QTY"
    SQLType="NUMERIC"/>
  <ViewAttribute
    Name="ReservedQty"
    IsUpdateable="false"
    IsPersistent="false"
    PrecisionRule="true"
    Type="java.math.BigDecimal"
    ColumnType="NUMBER"
    AliasName="RESERVED_QTY"
    Expression="RESERVED_QTY"
    SQLType="NUMERIC"/>
  <ViewAttribute
    Name="ReceivingQty"
    IsUpdateable="false"
    IsPersistent="false"
    PrecisionRule="true"
    Type="java.math.BigDecimal"
    ColumnType="NUMBER"
    AliasName="RECEIVING_QTY"
    Expression="RECEIVING_QTY"
    SQLType="NUMERIC"/>
  <ViewAttribute
    Name="LastUpdateDate"
    IsUpdateable="false"
    IsPersistent="false"
    IsNotNull="true"
    PrecisionRule="true"
    Type="java.sql.Timestamp"
    ColumnType="DATE"
    AliasName="LAST_UPDATE_DATE"
    Expression="LAST_UPDATE_DATE"
    SQLType="DATE"/>
  <ViewAttribute
    Name="SaleQty"
    IsUpdateable="false"
    IsPersistent="false"
    PrecisionRule="true"
    Type="java.math.BigDecimal"
    ColumnType="NUMBER"
    AliasName="SALE_QTY"
    Expression="SALE_QTY"
    SQLType="NUMERIC"/>
  <AttrArray Name="KeyAttributes">
    <Item Value="RowId1"/>
  </AttrArray>
</ViewObject>
